Metadata-Version: 1.0
Name: pair-in-list
Version: 0.1
Summary: Class including two functions to check if there are two elements in a list that add up to a specified sum
Home-page: UNKNOWN
Author: UNKNOWN
Author-email: UNKNOWN
License: UNKNOWN
Platform: UNKNOWN
